simplemetservice/__init__.py
simplemetservice-0.0.1.dist-info/METADATA
simplemetservice-0.0.1.dist-info/WHEEL
simplemetservice-0.0.1.dist-info/top_level.txt
simplemetservice-0.0.1.dist-info/RECORD
