Metadata-Version: 2.1
Name: simplemetservice
Version: 0.0.1
Summary: A simple python package for accessing MetService data, partly based on the project pymetservice
Home-page: https://pypi.org/project/simplemetservice
Author: d_man223
Author-email: kitclone@icloud.com
License: UNKNOWN
Platform: UNKNOWN
Requires-Dist: requests
